quantum_query_optimizer/__init__.py
quantum_query_optimizer/adm.py
quantum_query_optimizer/boolean_functions.py
quantum_query_optimizer/constraints.py
quantum_query_optimizer/span_program.py
quantum_query_optimizer/test.py
quantum_query_optimizer/visualize.py
quantum_query_optimizer-0.1.4.dist-info/LICENSE
quantum_query_optimizer-0.1.4.dist-info/METADATA
quantum_query_optimizer-0.1.4.dist-info/WHEEL
quantum_query_optimizer-0.1.4.dist-info/top_level.txt
quantum_query_optimizer-0.1.4.dist-info/RECORD
