Metadata-Version: 2.1
Name: quantum-query-optimizer
Version: 0.1.4
Summary: A toolkit to find the optimal quantum query complexity and query optimal quantum algorithm of arbitrary Boolean functions.
Home-page: https://github.com/rtealwitter/QuantumQueryOptimizer
Author: R. Teal Witter & Michael Czekanski
Author-email: rtealwitter@gmail.com, michaeltczekanski@gmail.com
Classifier: Programming Language :: Python :: 3
Classifier: License :: OSI Approved :: MIT License
Classifier: Operating System :: OS Independent
Requires-Python: >=3.6
License-File: LICENSE
